MANIFEST.in
README.rst
setup.py
docs/HISTORY.txt
ftw/__init__.py
ftw.protectinactive.egg-info/PKG-INFO
ftw.protectinactive.egg-info/SOURCES.txt
ftw.protectinactive.egg-info/dependency_links.txt
ftw.protectinactive.egg-info/entry_points.txt
ftw.protectinactive.egg-info/namespace_packages.txt
ftw.protectinactive.egg-info/not-zip-safe
ftw.protectinactive.egg-info/requires.txt
ftw.protectinactive.egg-info/top_level.txt
ftw/protectinactive/__init__.py
ftw/protectinactive/configure.zcml
ftw/protectinactive/registry.py
ftw/protectinactive/testing.py
ftw/protectinactive/traversalhook.py
ftw/protectinactive/upgrades.py
ftw/protectinactive/upgrades.zcml
ftw/protectinactive/locales/plone.pot
ftw/protectinactive/locales/de/LC_MESSAGES/plone.po
ftw/protectinactive/profiles/default/metadata.xml
ftw/protectinactive/profiles/default/registry.xml
ftw/protectinactive/tests/__init__.py
ftw/protectinactive/tests/dx_folder.py
ftw/protectinactive/tests/test_profiles.py
ftw/protectinactive/tests/test_traversal_hook.py